handsome/__init__.py
handsome/boy/__init__.py
handsome/boy/message.py
xzy_code-0.2.dist-info/METADATA
xzy_code-0.2.dist-info/WHEEL
xzy_code-0.2.dist-info/top_level.txt
xzy_code-0.2.dist-info/RECORD
