Metadata-Version: 2.1
Name: xzy-code
Version: 0.2
Summary: 徐梓煜
Author: xzy
License: UNKNOWN
Platform: UNKNOWN
